{
  "annotations": {
    "list": [
      {
        "builtIn": 1,
        "datasource": {
          "type": "grafana",
          "uid": "-- Grafana --"
        },
        "enable": true,
        "hide": true,
        "iconColor": "rgba(0, 211, 255, 1)",
        "name": "Annotations & Alerts",
        "target": {
          "limit": 100,
          "matchAny": false,
          "tags": [],
          "type": "dashboard"
        },
        "type": "dashboard"
      }
    ]
  },
  "editable": true,
  "fiscalYearStartMonth": 0,
  "graphTooltip": 0,
  "id": 2,
  "links": [],
  "liveNow": false,
  "panels": [
    {
      "datasource": {
        "type": "mysql",
        "uid": "P211906C1C32DB77E"
      },
      "description": "Total number of DISTINCT scanned IPs",
      "fieldConfig": {
        "defaults": {
          "color": {
            "mode": "thresholds"
          },
          "mappings": [],
          "thresholds": {
            "mode": "absolute",
            "steps": [
              {
                "color": "green",
                "value": null
              },
              {
                "color": "red",
                "value": 80
              }
            ]
          }
        },
        "overrides": []
      },
      "gridPos": {
        "h": 4,
        "w": 3,
        "x": 0,
        "y": 0
      },
      "id": 4,
      "options": {
        "colorMode": "background",
        "graphMode": "none",
        "justifyMode": "auto",
        "orientation": "auto",
        "reduceOptions": {
          "calcs": [
            "lastNotNull"
          ],
          "fields": "",
          "values": false
        },
        "textMode": "auto"
      },
      "pluginVersion": "9.3.2",
      "targets": [
        {
          "datasource": {
            "type": "mysql",
            "uid": "P211906C1C32DB77E"
          },
          "editorMode": "code",
          "format": "table",
          "rawQuery": true,
          "rawSql": "SELECT COUNT(DISTINCT(IP)) FROM scan",
          "refId": "A",
          "sql": {
            "columns": [
              {
                "parameters": [],
                "type": "function"
              }
            ],
            "groupBy": [
              {
                "property": {
                  "type": "string"
                },
                "type": "groupBy"
              }
            ],
            "limit": 50
          }
        }
      ],
      "title": "Total scanned IPs",
      "type": "stat"
    },
    {
      "datasource": {
        "type": "mysql",
        "uid": "P211906C1C32DB77E"
      },
      "description": "Number of DISTINCT scanned Titles (different of empty)",
      "fieldConfig": {
        "defaults": {
          "color": {
            "mode": "thresholds"
          },
          "mappings": [],
          "thresholds": {
            "mode": "absolute",
            "steps": [
              {
                "color": "green",
                "value": null
              },
              {
                "color": "red",
                "value": 80
              }
            ]
          }
        },
        "overrides": []
      },
      "gridPos": {
        "h": 4,
        "w": 3,
        "x": 3,
        "y": 0
      },
      "id": 5,
      "options": {
        "colorMode": "background",
        "graphMode": "none",
        "justifyMode": "auto",
        "orientation": "auto",
        "reduceOptions": {
          "calcs": [
            "lastNotNull"
          ],
          "fields": "",
          "values": false
        },
        "textMode": "auto"
      },
      "pluginVersion": "9.3.2",
      "targets": [
        {
          "datasource": {
            "type": "mysql",
            "uid": "P211906C1C32DB77E"
          },
          "editorMode": "code",
          "format": "table",
          "rawQuery": true,
          "rawSql": "SELECT COUNT(DISTINCT(HTTPtitle)) FROM scan WHERE HTTPtitle != \"\"",
          "refId": "A",
          "sql": {
            "columns": [
              {
                "parameters": [],
                "type": "function"
              }
            ],
            "groupBy": [
              {
                "property": {
                  "type": "string"
                },
                "type": "groupBy"
              }
            ],
            "limit": 50
          }
        }
      ],
      "title": "Total scanned Titles",
      "type": "stat"
    },
    {
      "datasource": {
        "type": "mysql",
        "uid": "P211906C1C32DB77E"
      },
      "description": "Number of DISTINCT scanned Titles (different of empty)",
      "fieldConfig": {
        "defaults": {
          "color": {
            "mode": "thresholds"
          },
          "mappings": [],
          "thresholds": {
            "mode": "absolute",
            "steps": [
              {
                "color": "green",
                "value": null
              },
              {
                "color": "red",
                "value": 80
              }
            ]
          }
        },
        "overrides": []
      },
      "gridPos": {
        "h": 4,
        "w": 3,
        "x": 6,
        "y": 0
      },
      "id": 6,
      "options": {
        "colorMode": "background",
        "graphMode": "none",
        "justifyMode": "auto",
        "orientation": "auto",
        "reduceOptions": {
          "calcs": [
            "lastNotNull"
          ],
          "fields": "",
          "values": false
        },
        "textMode": "auto"
      },
      "pluginVersion": "9.3.2",
      "targets": [
        {
          "datasource": {
            "type": "mysql",
            "uid": "P211906C1C32DB77E"
          },
          "editorMode": "code",
          "format": "table",
          "rawQuery": true,
          "rawSql": "SELECT COUNT(DISTINCT(Port)) FROM scan",
          "refId": "A",
          "sql": {
            "columns": [
              {
                "parameters": [],
                "type": "function"
              }
            ],
            "groupBy": [
              {
                "property": {
                  "type": "string"
                },
                "type": "groupBy"
              }
            ],
            "limit": 50
          }
        }
      ],
      "title": "Total scanned Ports ",
      "type": "stat"
    },
    {
      "datasource": {
        "type": "mysql",
        "uid": "P211906C1C32DB77E"
      },
      "fieldConfig": {
        "defaults": {
          "color": {
            "mode": "thresholds"
          },
          "custom": {
            "hideFrom": {
              "legend": false,
              "tooltip": false,
              "viz": false
            }
          },
          "mappings": [],
          "thresholds": {
            "mode": "absolute",
            "steps": [
              {
                "color": "green",
                "value": null
              },
              {
                "color": "red",
                "value": 80
              }
            ]
          }
        },
        "overrides": []
      },
      "gridPos": {
        "h": 6,
        "w": 12,
        "x": 12,
        "y": 0
      },
      "id": 8,
      "options": {
        "basemap": {
          "config": {},
          "name": "Layer 0",
          "type": "default"
        },
        "controls": {
          "mouseWheelZoom": true,
          "showAttribution": true,
          "showDebug": false,
          "showMeasure": false,
          "showScale": false,
          "showZoom": true
        },
        "layers": [
          {
            "config": {
              "showLegend": false,
              "style": {
                "color": {
                  "fixed": "dark-green"
                },
                "opacity": 0.8,
                "rotation": {
                  "fixed": 0,
                  "max": 360,
                  "min": -360,
                  "mode": "mod"
                },
                "size": {
                  "fixed": 5,
                  "max": 15,
                  "min": 2
                },
                "symbol": {
                  "fixed": "img/icons/marker/square.svg",
                  "mode": "fixed"
                },
                "textConfig": {
                  "fontSize": 12,
                  "offsetX": 0,
                  "offsetY": 0,
                  "textAlign": "center",
                  "textBaseline": "middle"
                }
              }
            },
            "location": {
              "mode": "auto"
            },
            "name": "Total Ports per Coord",
            "tooltip": true,
            "type": "markers"
          }
        ],
        "tooltip": {
          "mode": "details"
        },
        "view": {
          "allLayers": true,
          "id": "fit",
          "lastOnly": false,
          "lat": 0,
          "layer": "Layer 1",
          "lon": 0,
          "zoom": 12
        }
      },
      "pluginVersion": "9.3.2",
      "targets": [
        {
          "datasource": {
            "type": "mysql",
            "uid": "P211906C1C32DB77E"
          },
          "editorMode": "code",
          "format": "table",
          "rawQuery": true,
          "rawSql": "SELECT COUNT(Port) as CountPort, Latitude, Longitude FROM scan GROUP BY Latitude, Longitude",
          "refId": "A",
          "sql": {
            "columns": [
              {
                "parameters": [],
                "type": "function"
              }
            ],
            "groupBy": [
              {
                "property": {
                  "type": "string"
                },
                "type": "groupBy"
              }
            ],
            "limit": 50
          }
        }
      ],
      "title": "Map",
      "type": "geomap"
    },
    {
      "datasource": {
        "type": "mysql",
        "uid": "P211906C1C32DB77E"
      },
      "fieldConfig": {
        "defaults": {
          "color": {
            "mode": "thresholds"
          },
          "custom": {
            "align": "auto",
            "displayMode": "auto",
            "filterable": true,
            "inspect": false,
            "minWidth": 50
          },
          "mappings": [],
          "thresholds": {
            "mode": "absolute",
            "steps": [
              {
                "color": "green",
                "value": null
              },
              {
                "color": "red",
                "value": 80
              }
            ]
          }
        },
        "overrides": [
          {
            "matcher": {
              "id": "byName",
              "options": "Id"
            },
            "properties": [
              {
                "id": "custom.width",
                "value": 71
              }
            ]
          },
          {
            "matcher": {
              "id": "byName",
              "options": "Open"
            },
            "properties": [
              {
                "id": "custom.width",
                "value": 74
              },
              {
                "id": "thresholds",
                "value": {
                  "mode": "absolute",
                  "steps": [
                    {
                      "color": "dark-red",
                      "value": null
                    },
                    {
                      "color": "green",
                      "value": 1
                    }
                  ]
                }
              },
              {
                "id": "custom.displayMode",
                "value": "color-background-solid"
              }
            ]
          },
          {
            "matcher": {
              "id": "byName",
              "options": "Port"
            },
            "properties": [
              {
                "id": "custom.width",
                "value": 72
              }
            ]
          },
          {
            "matcher": {
              "id": "byName",
              "options": "HTTPstatus"
            },
            "properties": [
              {
                "id": "custom.width",
                "value": 95
              },
              {
                "id": "thresholds",
                "value": {
                  "mode": "absolute",
                  "steps": [
                    {
                      "color": "dark-blue",
                      "value": null
                    },
                    {
                      "color": "green",
                      "value": 200
                    },
                    {
                      "color": "semi-dark-red",
                      "value": 400
                    }
                  ]
                }
              },
              {
                "id": "custom.displayMode",
                "value": "color-background"
              }
            ]
          },
          {
            "matcher": {
              "id": "byName",
              "options": "Latency"
            },
            "properties": [
              {
                "id": "custom.width",
                "value": 86
              },
              {
                "id": "unit",
                "value": "ns"
              }
            ]
          },
          {
            "matcher": {
              "id": "byName",
              "options": "TLS"
            },
            "properties": [
              {
                "id": "custom.width",
                "value": 71
              }
            ]
          },
          {
            "matcher": {
              "id": "byName",
              "options": "HTTPfaviconService"
            },
            "properties": [
              {
                "id": "custom.width",
                "value": 141
              }
            ]
          },
          {
            "matcher": {
              "id": "byName",
              "options": "HTTPserver"
            },
            "properties": [
              {
                "id": "custom.width",
                "value": 138
              }
            ]
          },
          {
            "matcher": {
              "id": "byName",
              "options": "HTTPfavicon"
            },
            "properties": [
              {
                "id": "custom.width",
                "value": 120
              }
            ]
          },
          {
            "matcher": {
              "id": "byName",
              "options": "ServiceInfo"
            },
            "properties": [
              {
                "id": "custom.width",
                "value": 167
              },
              {
                "id": "custom.displayMode",
                "value": "json-view"
              }
            ]
          },
          {
            "matcher": {
              "id": "byName",
              "options": "INET_NTOA(IP)"
            },
            "properties": [
              {
                "id": "custom.width",
                "value": 153
              }
            ]
          },
          {
            "matcher": {
              "id": "byName",
              "options": "PortService"
            },
            "properties": [
              {
                "id": "custom.width",
                "value": 150
              }
            ]
          }
        ]
      },
      "gridPos": {
        "h": 17,
        "w": 24,
        "x": 0,
        "y": 6
      },
      "id": 2,
      "options": {
        "footer": {
          "enablePagination": true,
          "fields": "",
          "reducer": [
            "sum"
          ],
          "show": false
        },
        "showHeader": true,
        "sortBy": []
      },
      "pluginVersion": "9.3.2",
      "targets": [
        {
          "dataset": "port_scraper",
          "datasource": {
            "type": "mysql",
            "uid": "P211906C1C32DB77E"
          },
          "editorMode": "code",
          "format": "table",
          "rawQuery": true,
          "rawSql": "SELECT\n\tId,\n\tINET_NTOA(IP),\n\tscan.Port,\n\tport.Service as PortService,\n\tOpen,\n\tLatency,\n\tHTTPstatus,\n\tHTTPtitle,\n\tHTTPserver,\n\tHTTPfavicon,\n\tfavicon.Service as HTTPfaviconService,\n\tServiceInfo,\n\tTLS,\n\tTLScertificate,\n\tCountryCode,\n\tDistrict,\n\tCity,\n\tLatitude,\n\tLongitude,\n\tTimestamp\nFROM port_scraper.scan \nLEFT JOIN port_scraper.favicon ON scan.HTTPfavicon  = favicon.Hash \nLEFT JOIN port_scraper.port ON scan.Port  = port.Port \nWHERE $__timeFilter(Timestamp)",
          "refId": "A",
          "sql": {
            "columns": [
              {
                "name": "VARIANCE",
                "parameters": [
                  {
                    "name": "HTTPserver",
                    "type": "functionParameter"
                  }
                ],
                "type": "function"
              }
            ],
            "groupBy": [
              {
                "property": {
                  "type": "string"
                },
                "type": "groupBy"
              }
            ],
            "limit": 50
          },
          "table": "scan"
        }
      ],
      "title": "scan table",
      "transformations": [
        {
          "id": "organize",
          "options": {
            "excludeByName": {
              "City": true,
              "CountryCode": true,
              "District": true,
              "Latitude": true,
              "Longitude": true,
              "TLScertificate": true
            },
            "indexByName": {},
            "renameByName": {}
          }
        }
      ],
      "type": "table"
    }
  ],
  "schemaVersion": 37,
  "style": "dark",
  "tags": [],
  "templating": {
    "list": []
  },
  "time": {
    "from": "now-30d",
    "to": "now"
  },
  "timepicker": {},
  "timezone": "",
  "title": "Port Scraper",
  "uid": "swLypXcVk",
  "version": 4,
  "weekStart": ""
}